odoo/addons/account_move_base_import/README.rst
odoo/addons/account_move_base_import/__init__.py
odoo/addons/account_move_base_import/__manifest__.py
odoo/addons/account_move_base_import/data/completion_rule_data.xml
odoo/addons/account_move_base_import/demo/statement.csv
odoo/addons/account_move_base_import/demo/statement.xls
odoo/addons/account_move_base_import/i18n/account_move_base_import.pot
odoo/addons/account_move_base_import/i18n/am.po
odoo/addons/account_move_base_import/i18n/ar.po
odoo/addons/account_move_base_import/i18n/bg.po
odoo/addons/account_move_base_import/i18n/bs.po
odoo/addons/account_move_base_import/i18n/ca.po
odoo/addons/account_move_base_import/i18n/cs.po
odoo/addons/account_move_base_import/i18n/da.po
odoo/addons/account_move_base_import/i18n/de.po
odoo/addons/account_move_base_import/i18n/el_GR.po
odoo/addons/account_move_base_import/i18n/en_GB.po
odoo/addons/account_move_base_import/i18n/es.po
odoo/addons/account_move_base_import/i18n/es_AR.po
odoo/addons/account_move_base_import/i18n/es_CL.po
odoo/addons/account_move_base_import/i18n/es_CO.po
odoo/addons/account_move_base_import/i18n/es_CR.po
odoo/addons/account_move_base_import/i18n/es_DO.po
odoo/addons/account_move_base_import/i18n/es_EC.po
odoo/addons/account_move_base_import/i18n/es_ES.po
odoo/addons/account_move_base_import/i18n/es_MX.po
odoo/addons/account_move_base_import/i18n/es_PE.po
odoo/addons/account_move_base_import/i18n/es_PY.po
odoo/addons/account_move_base_import/i18n/es_VE.po
odoo/addons/account_move_base_import/i18n/et.po
odoo/addons/account_move_base_import/i18n/eu.po
odoo/addons/account_move_base_import/i18n/fa.po
odoo/addons/account_move_base_import/i18n/fi.po
odoo/addons/account_move_base_import/i18n/fr.po
odoo/addons/account_move_base_import/i18n/fr_CA.po
odoo/addons/account_move_base_import/i18n/fr_CH.po
odoo/addons/account_move_base_import/i18n/gl.po
odoo/addons/account_move_base_import/i18n/gl_ES.po
odoo/addons/account_move_base_import/i18n/he.po
odoo11_addon_account_move_base_import-11.0.1.0.0.99.dev8.dist-info/METADATA
odoo11_addon_account_move_base_import-11.0.1.0.0.99.dev8.dist-info/WHEEL
odoo11_addon_account_move_base_import-11.0.1.0.0.99.dev8.dist-info/top_level.txt
odoo11_addon_account_move_base_import-11.0.1.0.0.99.dev8.dist-info/RECORD
